{
  "participants": [
    {
      "id": "marketing_team",
      "name": "Marketing Team",
      "type": "pool"
    }
  ],
  "tasks": [
    {
      "id": "convene_briefing",
      "name": "Convene at 6:30AM for Briefing",
      "type": "task",
      "participant": "marketing_team"
    },
    {
      "id": "launch_daily_ad_campaign",
      "name": "Launch Daily Ad Campaign",
      "type": "task",
      "participant": "marketing_team"
    },
    {
      "id": "review_latest_analytics",
      "name": "Review Latest Analytics",
      "type": "task",
      "participant": "marketing_team"
    },
    {
      "id": "finalize_presentation",
      "name": "Finalize Presentation",
      "type": "task",
      "participant": "marketing_team"
    },
    {
      "id": "drive_to_clients_office",
      "name": "Drive to Clients Office in Namur",
      "type": "task",
      "participant": "marketing_team"
    },
    {
      "id": "discuss_campaign_strategy",
      "name": "Discuss Campaign Strategy",
      "type": "task",
      "participant": "marketing_team"
    },
    {
      "id": "deliver_pitch",
      "name": "Deliver Pitch",
      "type": "task",
      "participant": "marketing_team"
    },
    {
      "id": "return_to_office",
      "name": "Return to Office",
      "type": "task",
      "participant": "marketing_team"
    }
  ],
  "events": [
    {
      "id": "start_marketing",
      "name": "Start",
      "type": "startEvent",
      "participant": "marketing_team",
      "eventDefinition": "none"
    },
    {
      "id": "end_marketing",
      "name": "End",
      "type": "endEvent",
      "participant": "marketing_team",
      "eventDefinition": "none"
    }
  ],
  "gateways": [
    {
      "id": "gateway_parallel_split",
      "name": "Start Concurrent Tasks",
      "type": "parallelGateway",
      "participant": "marketing_team",
      "gatewayDirection": "diverging"
    },
    {
      "id": "gateway_parallel_join",
      "name": "Concurrent Tasks Complete",
      "type": "parallelGateway",
      "participant": "marketing_team",
      "gatewayDirection": "converging"
    }
  ],
  "sequence_flows": [
    { "id": "sf1", "from": "start_marketing", "to": "convene_briefing" },
    { "id": "sf2", "from": "convene_briefing", "to": "launch_daily_ad_campaign" },
    { "id": "sf3", "from": "launch_daily_ad_campaign", "to": "review_latest_analytics" },
    { "id": "sf4", "from": "review_latest_analytics", "to": "finalize_presentation" },
    { "id": "sf5", "from": "finalize_presentation", "to": "gateway_parallel_split" },
    { "id": "sf6", "from": "gateway_parallel_split", "to": "drive_to_clients_office" },
    { "id": "sf7", "from": "gateway_parallel_split", "to": "discuss_campaign_strategy" },
    { "id": "sf8", "from": "drive_to_clients_office", "to": "gateway_parallel_join" },
    { "id": "sf9", "from": "discuss_campaign_strategy", "to": "gateway_parallel_join" },
    { "id": "sf10", "from": "gateway_parallel_join", "to": "deliver_pitch" },
    { "id": "sf11", "from": "deliver_pitch", "to": "return_to_office" },
    { "id": "sf12", "from": "return_to_office", "to": "end_marketing" }
  ],
  "message_flows": [],
  "data": [],
  "data_associations": []
}